{
  "list": [
    {
      "_key": 0,
      "_hp": 800.0,
      "_atk": 19.0,
      "_def": 50.0,
      "_accuracy": 35.0,
      "_evade": 45.0,
      "_name": "4F1",
      "_shipClass": 0,
      "_star": 4,
      "_maxCombatSlot": 4
    },
    {
      "_key": 1,
      "_hp": 1100.0,
      "_atk": 19.0,
      "_def": 65.0,
      "_accuracy": 28.0,
      "_evade": 30.0,
      "_name": "4D1",
      "_shipClass": 1,
      "_star": 4,
      "_maxCombatSlot": 6
    },
    {
      "_key": 2,
      "_hp": 1600.0,
      "_atk": 19.0,
      "_def": 85.0,
      "_accuracy": 24.0,
      "_evade": 15.0,
      "_name": "4C1",
      "_shipClass": 2,
      "_star": 4,
      "_maxCombatSlot": 8
    },
    {
      "_key": 3,
      "_hp": 2200.0,
      "_atk": 19.0,
      "_def": 115.0,
      "_accuracy": 15.0,
      "_evade": 5.0,
      "_name": "4B1",
      "_shipClass": 3,
      "_star": 4,
      "_maxCombatSlot": 10
    },
    {
      "_key": 4,
      "_hp": 4200.0,
      "_atk": 22.0,
      "_def": 145.0,
      "_accuracy": 11.0,
      "_evade": 1.0,
      "_name": "5T1",
      "_shipClass": 4,
      "_star": 5,
      "_maxCombatSlot": 12
    }
  ]
}